dbs_image_utils/__init__.py
dbs_image_utils/histogram_standartisation.py
dbs_image_utils/mask.py
dbs_image_utils/mer_support.py
dbs_image_utils/nets.py
dbs_pure_lib-0.0.2.dist-info/licenses/LICENSE.txt
dbs_pure_lib-0.0.2.dist-info/METADATA
dbs_pure_lib-0.0.2.dist-info/WHEEL
dbs_pure_lib-0.0.2.dist-info/top_level.txt
dbs_pure_lib-0.0.2.dist-info/RECORD
